credential_manager.py
main.py
rbxclient/__init__.py
rbxclient/client.py
rbxclient/deeplink.py
roblox_mcp_server-1.0.0.dist-info/licenses/LICENSE
roblox_mcp_server-1.0.0.dist-info/METADATA
roblox_mcp_server-1.0.0.dist-info/WHEEL
roblox_mcp_server-1.0.0.dist-info/entry_points.txt
roblox_mcp_server-1.0.0.dist-info/top_level.txt
roblox_mcp_server-1.0.0.dist-info/RECORD
