Metadata-Version: 2.4
Name: roblox-mcp-server
Version: 1.0.0
Summary: A Roblox MCP server implementation using FastMCP for tools.
Home-page: https://github.com/h053698/roblox-mcp-server
Author: Yuchan Han
Author-email: Yuchan Han <serltretu24@gmail.com>
License: MIT License
Classifier: Programming Language :: Python :: 3
Classifier: License :: OSI Approved :: MIT License
Classifier: Operating System :: OS Independent
Classifier: Topic :: Games/Entertainment
Classifier: Topic :: Software Development :: Libraries :: Python Modules
Requires-Python: >=3.6
License-File: LICENSE
Requires-Dist: fastmcp
Requires-Dist: keyring
Requires-Dist: tk
Dynamic: author
Dynamic: home-page
Dynamic: license-file
Dynamic: requires-python
